slvs/__init__.py
slvs/solvespace.pyd
slvs/solvespace.pyi
slvs-3.2rc1.dist-info/METADATA
slvs-3.2rc1.dist-info/WHEEL
slvs-3.2rc1.dist-info/licenses/COPYING.txt
slvs-3.2rc1.dist-info/RECORD
